autorelease/__init__.py
autorelease/_installed_version.py
autorelease/_version.py
autorelease/check_runners.py
autorelease/git_repo_checks.py
autorelease/github_release.py
autorelease/release_notes.py
autorelease/root_dir_checks.py
autorelease/script_utils.py
autorelease/utils.py
autorelease/version.py
autorelease/version_checks.py
autorelease/gh_actions_stages/autorelease-default-env.sh
autorelease/gh_actions_stages/autorelease-deploy.yml
autorelease/gh_actions_stages/autorelease-gh-rel.yml
autorelease/gh_actions_stages/autorelease-prep.yml
autorelease/gh_api4/__init__.py
autorelease/gh_api4/notes4.py
autorelease/gh_api4/pull_requests.py
autorelease/gh_api4/query_runner.py
autorelease/gh_api4/releases.py
autorelease/gh_api4/utils.py
autorelease/scripts/__init__.py
autorelease/scripts/bump_dev_version.py
autorelease/scripts/check.py
autorelease/scripts/cli.py
autorelease/scripts/release.py
autorelease/scripts/vendor.py
autorelease/scripts/write_release_notes.py
autorelease/tests/__init__.py
autorelease/tests/test_bump_dev_version.py
autorelease/tests/test_check_runners.py
autorelease/tests/test_version.py
autorelease-0.7.0.data/scripts/deploy-pypi
autorelease-0.7.0.data/scripts/install-testpypi
autorelease-0.7.0.data/scripts/test-testpypi
autorelease-0.7.0.dist-info/licenses/LICENSE
autorelease-0.7.0.dist-info/METADATA
autorelease-0.7.0.dist-info/WHEEL
autorelease-0.7.0.dist-info/entry_points.txt
autorelease-0.7.0.dist-info/top_level.txt
autorelease-0.7.0.dist-info/RECORD
