Metadata-Version: 2.4
Name: autorelease
Version: 0.7.0
Summary: Tools to keep the release process clean.
Home-page: https://github.com/dwhswenson/autorelease
Author: David W.H. Swenson
Author-email: dwhs@hyperblazer.net
License: MIT
Classifier: Development Status :: 4 - Beta
Classifier: Environment :: Console
Classifier: Environment :: MacOS X
Classifier: Environment :: Win32 (MS Windows)
Classifier: Intended Audience :: Developers
Classifier: License :: OSI Approved :: MIT License
Classifier: Natural Language :: English
Classifier: Operating System :: MacOS :: MacOS X
Classifier: Operating System :: Microsoft :: Windows
Classifier: Operating System :: POSIX
Classifier: Programming Language :: Python :: 2.7
Classifier: Programming Language :: Python :: 3.6
Classifier: Programming Language :: Python :: 3.7
Classifier: Programming Language :: Python :: 3.8
Classifier: Topic :: Software Development :: Testing
Requires-Python: >=3.7
License-File: LICENSE
Requires-Dist: packaging
Requires-Dist: pyyaml
Requires-Dist: gitpython
Requires-Dist: future
Requires-Dist: requests
Requires-Dist: python-dateutil
Requires-Dist: click
Requires-Dist: setuptools
Dynamic: license-file
